{"textures":{"0":"modelengine:entity/nm_grizzly_bear_baby_texture"},"elements":[{"from":[6.5,1.75,6.5],"to":[9.5,8.75,9.5],"faces":{"east":{"uv":[3.75,10.0,4.5,11.75],"tintindex":0,"rotation":0,"texture":"#0"},"south":{"uv":[4.5,10.0,5.25,11.75],"tintindex":0,"rotation":0,"texture":"#0"},"north":{"uv":[10.0,1.75,10.75,3.5],"tintindex":0,"rotation":0,"texture":"#0"},"west":{"uv":[5.25,10.0,6.0,11.75],"tintindex":0,"rotation":0,"texture":"#0"},"up":{"uv":[11.0,5.75,10.25,5.0],"tintindex":0,"rotation":0,"texture":"#0"},"down":{"uv":[11.25,0.0,10.5,0.75],"tintindex":0,"rotation":0,"texture":"#0"}}}],"display":{"gui":{"rotation":[30,225,0]}}}